{"data": [{"challenge_id": 1, "challenge": {"category": "misc", "name": "irc", "value": 1}, "user": 75399, "team": 112535, "date": "2019-06-01T08:11:13+00:00", "type": "correct", "id": 3024}, {"challenge_id": 10, "challenge": {"category": "pwnable", "name": "overfloat", "value": 100}, "user": 75399, "team": 112535, "date": "2019-06-01T10:08:51+00:00", "type": "correct", "id": 3599}, {"challenge_id": 22, "challenge": {"category": "web", "name": "products manager", "value": 100}, "user": 75399, "team": 112535, "date": "2019-06-01T21:30:18+00:00", "type": "correct", "id": 7047}, {"challenge_id": 24, "challenge": {"category": "reversing", "name": "imageprot", "value": 100}, "user": 75399, "team": 112535, "date": "2019-06-01T23:57:14+00:00", "type": "correct", "id": 7604}, {"challenge_id": 17, "challenge": {"category": "pwnable", "name": "otp_server", "value": 410}, "user": 75399, "team": 112535, "date": "2019-06-02T18:12:58+00:00", "type": "correct", "id": 11338}, {"challenge_id": 25, "challenge": {"category": "reversing", "name": "go_get_the_flag", "value": 453}, "user": 75399, "team": 112535, "date": "2019-06-02T19:58:16+00:00", "type": "correct", "id": 11736}, {"challenge_id": 26, "challenge": {"category": "reversing", "name": "SOMBRERO ROJO (part 1)", "value": 424}, "user": 75399, "team": 112535, "date": "2019-06-02T21:18:50+00:00", "type": "correct", "id": 11961}, {"challenge_id": 27, "challenge": {"category": "reversing", "name": "SOMBRERO ROJO (part 2)", "value": 935}, "user": 75399, "team": 112535, "date": "2019-06-02T22:19:59+00:00", "type": "correct", "id": 12099}], "success": true}
